renaming/__init__.py
renaming/__main__.py
renaming/command_line.py
renaming-0.1.3.dist-info/LICENSE
renaming-0.1.3.dist-info/METADATA
renaming-0.1.3.dist-info/WHEEL
renaming-0.1.3.dist-info/entry_points.txt
renaming-0.1.3.dist-info/top_level.txt
renaming-0.1.3.dist-info/RECORD
