Metadata-Version: 2.1
Name: renaming
Version: 0.1.3
Summary: A cli tool to rename certain files according to a certain pattern.
Author-email: Kyan <kai@kyan001.com>
License: BSD 3-Clause License
Project-URL: Homepage, https://github.com/kyan001/PyRenaming
Project-URL: Changelog, https://github.com/kyan001/PyRenaming/blob/master/CHANGELOG.md
Project-URL: Issue Tracker, https://github.com/kyan001/PyRenaming/issues
Project-URL: Source Code, https://github.com/kyan001/PyRenaming
Keywords: python3,renaming,rename,cli
Classifier: Intended Audience :: Developers
Classifier: Intended Audience :: End Users/Desktop
Classifier: License :: OSI Approved :: BSD License
Classifier: Programming Language :: Python :: 3
Classifier: Programming Language :: Python :: 3 :: Only
Requires-Python: >=3.8
License-File: LICENSE
Requires-Dist: consoleiotools
Requires-Dist: consolecmdtools >=6.4.0
Provides-Extra: dev
Requires-Dist: build ; extra == 'dev'
Requires-Dist: twine ; extra == 'dev'
